MANIFEST.in
Makefile
README.md
__init__.py
setup.py
.eggs/pytest_runner-4.2-py2.7.egg/ptr.py
benchmarks/bm_call_method.py
benchmarks/bm_call_simple.py
benchmarks/call.py
benchmarks/comprehension.py
benchmarks/concurrent.py
benchmarks/dict.py
benchmarks/generator.py
benchmarks/list.py
benchmarks/loop.py
benchmarks/tuple.py
grumpy_runtime/__init__.py
lib/__builtin__.py
lib/_random.py
lib/_syscall.py
lib/cStringIO.py
lib/errno.py
lib/exceptions.py
lib/itertools.py
lib/itertools_test.py
lib/math.py
lib/math_test.py
lib/os_test.py
lib/random_test.py
lib/select_.py
lib/stat.py
lib/sys.py
lib/sys_test.py
lib/tempfile.py
lib/tempfile_test.py
lib/thread.py
lib/time.py
lib/time_test.py
lib/types_test.py
lib/weetest.py
lib/weetest_test.py
lib/os/__init__.py
lib/os/path.py
lib/os/path_test.py
runtime/baseexception.go
runtime/baseexception_test.go
runtime/basestring.go
runtime/basestring_test.go
runtime/bool.go
runtime/bool_test.go
runtime/builtin_types.go
runtime/builtin_types_test.go
runtime/bytearray.go
runtime/bytearray_test.go
runtime/code.go
runtime/code_test.go
runtime/complex.go
runtime/complex_test.go
runtime/core.go
runtime/core_test.go
runtime/descriptor.go
runtime/descriptor_test.go
runtime/dict.go
runtime/dict_test.go
runtime/doc.go
runtime/exceptions.go
runtime/file.go
runtime/file_test.go
runtime/float.go
runtime/float_test.go
runtime/frame.go
runtime/frame_test.go
runtime/function.go
runtime/function_test.go
runtime/generator.go
runtime/generator_test.go
runtime/int.go
runtime/int_test.go
runtime/list.go
runtime/list_test.go
runtime/long.go
runtime/long_test.go
runtime/method.go
runtime/method_test.go
runtime/module.go
runtime/module_test.go
runtime/native.go
runtime/native_test.go
runtime/numeric.go
runtime/object.go
runtime/object_test.go
runtime/param.go
runtime/param_test.go
runtime/range.go
runtime/range_test.go
runtime/seq.go
runtime/seq_test.go
runtime/set.go
runtime/set_test.go
runtime/slice.go
runtime/slice_test.go
runtime/slots.go
runtime/slots_test.go
