Metadata-Version: 1.2
Name: grumpy-runtime
Version: 0.2.1
Summary: Grumpy Runtime & Transpiler
Home-page: https://github.com/google/grumpy
Author: Dylan Trotter et al.
Maintainer: Alan Justino et al.
Maintainer-email: alan.justino@yahoo.com.br
License: Apache Software License 2.0
Keywords: grumpy_runtime
Platform: UNKNOWN
Classifier: Development Status :: 2 - Pre-Alpha
Classifier: Intended Audience :: Developers
Classifier: License :: OSI Approved :: Apache Software License
Classifier: Natural Language :: English
Classifier: Programming Language :: Python :: 2
Classifier: Programming Language :: Python :: 2.7
Requires: grumpy_tools
Requires-Python: ~=2.7.0
